README.md
goto-http-redirect-server.py
setup.py
goto_http_redirect_server/__init__.py
goto_http_redirect_server/__main__.py
goto_http_redirect_server/goto_http_redirect_server.py
service/goto_http_redirect_server.conf
service/goto_http_redirect_server.service
service/goto_http_redirect_server.sh
service/service-install.sh
service/service-uninstall.sh
goto_http_redirect_server-1.2.1.dist-info/LICENSE
goto_http_redirect_server-1.2.1.dist-info/LICENSE-www.kryogenix.org
goto_http_redirect_server-1.2.1.dist-info/METADATA
goto_http_redirect_server-1.2.1.dist-info/WHEEL
goto_http_redirect_server-1.2.1.dist-info/entry_points.txt
goto_http_redirect_server-1.2.1.dist-info/top_level.txt
goto_http_redirect_server-1.2.1.dist-info/RECORD
