Metadata-Version: 2.1
Name: goto-http-redirect-server
Version: 1.2.1
Summary: The "Go To" HTTP Redirect Server for sharing dynamic shortcut URLs on your network.
Home-page: https://pypi.org/project/goto-http-redirect-server/
Author: jtmoon79
License: MIT License
Project-URL: Source, https://github.com/jtmoon79/goto_http_redirect_server
Project-URL: Bug Reports, https://github.com/jtmoon79/goto_http_redirect_server/issues
Project-URL: CI (Azure), https://dev.azure.com/jtmmoon/goto_http_redirect_server
Project-URL: CI (CircleCI), https://circleci.com/gh/jtmoon79/goto_http_redirect_server
Keywords: http-server redirect-urls shortcuts shorturl shorturl-servicesshorturls url-shortener
Classifier: Development Status :: 5 - Production/Stable
Classifier: Environment :: Console
Classifier: Operating System :: OS Independent
Classifier: Natural Language :: English
Classifier: License :: OSI Approved :: MIT License
Classifier: Programming Language :: Python :: 3.6
Classifier: Programming Language :: Python :: 3.7
Classifier: Programming Language :: Python :: 3.8
Classifier: Programming Language :: Python :: 3.9
Classifier: Programming Language :: Python :: 3.10
Classifier: Programming Language :: Python :: 3.11
Classifier: Programming Language :: Python :: 3 :: Only
Classifier: Topic :: Internet :: WWW/HTTP :: HTTP Servers
Requires-Python: >=3.6
License-File: LICENSE
License-File: LICENSE-www.kryogenix.org
Provides-Extra: build
Requires-Dist: pip ; extra == 'build'
Requires-Dist: setuptools (>=44) ; extra == 'build'
Requires-Dist: twine (>=3.3) ; extra == 'build'
Requires-Dist: wheel ; extra == 'build'
Provides-Extra: development
Requires-Dist: flake8 (==6.0.0) ; extra == 'development'
Requires-Dist: mypy (==0.991) ; extra == 'development'
Requires-Dist: pytest (==7.2.0) ; extra == 'development'
Requires-Dist: pytest-cov (==4.0.0) ; extra == 'development'
Requires-Dist: pytest-timeout (==2.1.0) ; extra == 'development'
Requires-Dist: yamllint (==1.28.0) ; extra == 'development'
Provides-Extra: development-flake8
Requires-Dist: flake8 (==6.0.0) ; extra == 'development-flake8'
Provides-Extra: development-mypy
Requires-Dist: mypy (==0.991) ; extra == 'development-mypy'
Provides-Extra: development-pytest
Requires-Dist: pytest (==7.2.0) ; extra == 'development-pytest'
Requires-Dist: pytest-cov (==4.0.0) ; extra == 'development-pytest'
Requires-Dist: pytest-timeout (==2.1.0) ; extra == 'development-pytest'
Provides-Extra: development-yamllint
Requires-Dist: yamllint (==1.28.0) ; extra == 'development-yamllint'
Provides-Extra: readme
Requires-Dist: md-toc ; extra == 'readme'
